benchmarks/__init__.py
benchmarks/core.py
benchmarks/demo_system.py
benchmarks/graph_generation.py
benchmarks/reporting.py
benchmarks/test_infrastructure.py
benchmarks/traversal_algorithms.py
klotho/__init__.py
klotho/chronos/__init__.py
klotho/chronos/rhythm_pairs/__init__.py
klotho/chronos/rhythm_pairs/rhythm_pair.py
klotho/chronos/rhythm_trees/__init__.py
klotho/chronos/rhythm_trees/algorithms.py
klotho/chronos/rhythm_trees/meas.py
klotho/chronos/rhythm_trees/rhythm_tree.py
klotho/chronos/temporal_units/__init__.py
klotho/chronos/temporal_units/algorithms.py
klotho/chronos/temporal_units/temporal.py
klotho/chronos/utils/__init__.py
klotho/chronos/utils/beat.py
klotho/chronos/utils/tempo.py
klotho/chronos/utils/time_conversion.py
klotho/dynatos/__init__.py
klotho/dynatos/dynamics/__init__.py
klotho/dynatos/dynamics/dynamics.py
klotho/dynatos/dynamics/utils/__init__.py
klotho/dynatos/dynamics/utils/amplitude.py
klotho/dynatos/dynamics/utils/scaling.py
klotho/dynatos/envelopes/__init__.py
klotho/dynatos/envelopes/envelopes.py
klotho/dynatos/envelopes/utils/__init__.py
klotho/dynatos/envelopes/utils/curves.py
klotho/semeios/__init__.py
klotho/semeios/animation/__init__.py
klotho/semeios/animation/animate.py
klotho/semeios/maquettes/__init__.py
klotho/semeios/maquettes/clip.py
klotho/semeios/maquettes/timeline.py
klotho/semeios/midi/__init__.py
klotho/semeios/midi/midi_export.py
klotho/semeios/notation/__init__.py
klotho/semeios/notation/notation.py
klotho/semeios/notation/notation_OLD.py
klotho/semeios/notelists/__init__.py
klotho/semeios/notelists/allolib.py
klotho/semeios/notelists/supercollider.py
klotho/semeios/visualization/__init__.py
klotho/semeios/visualization/plots.py
klotho/thetos/__init__.py
klotho/thetos/types.py
klotho/thetos/composition/__init__.py
klotho/thetos/composition/compositional.py
klotho/thetos/instruments/__init__.py
klotho/thetos/instruments/instrument.py
klotho/thetos/parameters/__init__.py
klotho/thetos/parameters/instruments.py
klotho_cac-3.15.1.dist-info/licenses/LICENSE
klotho_cac-3.15.1.dist-info/METADATA
klotho_cac-3.15.1.dist-info/WHEEL
klotho_cac-3.15.1.dist-info/top_level.txt
klotho_cac-3.15.1.dist-info/RECORD
