Metadata-Version: 2.4
Name: klotho-cac
Version: 3.15.1
Summary: Graph-Oriented Computer-Assisted Composition in Python
Home-page: https://github.com/kr4g/Klotho
Author: Ryan Millett
Author-email: rmillett@mat.ucsb.edu
License: CC-BY-SA-4.0
Classifier: Development Status :: 3 - Alpha
Classifier: License :: Other/Proprietary License
Classifier: Programming Language :: Python :: 3
Classifier: Programming Language :: Python :: 3.10
Classifier: Programming Language :: Python :: 3.11
Classifier: Programming Language :: Python :: 3 :: Only
Classifier: Topic :: Multimedia :: Sound/Audio
Classifier: Topic :: Artistic Software
Requires-Python: >=3.10
License-File: LICENSE
Requires-Dist: pandas
Requires-Dist: numpy
Requires-Dist: sympy
Requires-Dist: regex
Requires-Dist: matplotlib
Requires-Dist: tabulate
Requires-Dist: networkx
Requires-Dist: rustworkx
Requires-Dist: scipy
Requires-Dist: python-osc
Requires-Dist: abjad
Requires-Dist: mido
Requires-Dist: pyfluidsynth
Requires-Dist: soundfile
Requires-Dist: IPython
Requires-Dist: panel
Requires-Dist: bokeh
Requires-Dist: jupyter_bokeh
Requires-Dist: diversipy
Provides-Extra: docs
Requires-Dist: sphinx>=7.0.0; extra == "docs"
Requires-Dist: sphinx-rtd-theme; extra == "docs"
Requires-Dist: numpydoc; extra == "docs"
Requires-Dist: sphinx-autodoc-typehints; extra == "docs"
Requires-Dist: sphinx-copybutton; extra == "docs"
Provides-Extra: dev
Requires-Dist: pytest; extra == "dev"
Requires-Dist: sphinx>=7.0.0; extra == "dev"
Requires-Dist: sphinx-rtd-theme; extra == "dev"
Requires-Dist: numpydoc; extra == "dev"
Requires-Dist: sphinx-autodoc-typehints; extra == "dev"
Requires-Dist: sphinx-copybutton; extra == "dev"
Dynamic: author
Dynamic: author-email
Dynamic: classifier
Dynamic: description
Dynamic: description-content-type
Dynamic: home-page
Dynamic: license
Dynamic: license-file
Dynamic: provides-extra
Dynamic: requires-dist
Dynamic: requires-python
Dynamic: summary
